<ClinicalDocument xmlns="urn:hl7-org:v3" xmlns:sdtc="urn:hl7-org:sdtc" xmlns:xsi="http://www.w3.org/2001/XMLSchema-instance"><realmCode code="US"/><typeId extension="POCD_HD000040" root="2.16.840.1.113883.1.3"/><!-- [C-CDA R1.1] US Realm Header --><templateId root="2.16.840.1.113883.10.20.22.1.1"/><!-- [C-CDA R2.1] US Realm Header (V3) --><templateId extension="2015-08-01" root="2.16.840.1.113883.10.20.22.1.1"/><!-- [eICR R2 STU1.1] Initial Public Health Case Report Document (eICR) (V2) --><templateId extension="2016-12-01" root="2.16.840.1.113883.10.20.15.2"/><id extension="1" root="a3266d94-ce19-11ec-81e1-8465ad080d41"/><code code="55751-2" codeSystem="2.16.840.1.113883.6.1" codeSystemName="LOINC" displayName="Public Health Case Report"/><title>Initial Public Health Case Report</title><effectiveTime value="20220507112300-0400"/><confidentialityCode code="N" codeSystem="2.16.840.1.113883.5.25"/><languageCode code="en"/><setId extension="93" root="1.3.6.1.4.1.24310"/><versionNumber value="64"/><recordTarget><patientRole><!-- Patient Identifiers--><id extension="0000008807" root="2.25.208734791866360805618646170698166832449"/><id extension="9244" root="2.25.208734791866360805618646170698166832449"/><id extension="8589d444-a267-11ec-81e0-9e7eef92c510" root="2.25.208734791866360805618646170698166832449"/><!-- Patient Address --><addr use="HP"><streetAddressLine>1 main street</streetAddressLine><city>brockton</city><state>CA</state><postalCode>90210</postalCode><country>US</country><useablePeriod xsi:type="IVL_TS"><low nullFlavor="UNK"/><high nullFlavor="NA"/></useablePeriod></addr><!-- Patient Telephone/Contact Details --><telecom use="HP" value="tel:+1(789)785-8594"/><patient><!-- Patient Name --><name use="L"><family>CUTLA</family><given>CARETEAM</given></name><!-- Administrative Gender --><administrativeGenderCode code="M" codeSystem="2.16.840.1.113883.5.1" codeSystemName="AdministrativeGender" displayName="Male"/><!-- Birthdate --><birthTime value="19600912"/><!-- Deceased Indicator --><sdtc:deceasedInd value="false"/><!-- Marital Status --><maritalStatusCode code="S" codeSystem="2.16.840.1.113883.5.2" codeSystemName="MaritalStatus" displayName="Never Married"/><!-- Religious Affiliation --><religiousAffiliationCode nullFlavor="UNK"/><!-- Patient Race --><raceCode code="2106-3" codeSystem="2.16.840.1.113883.6.238" codeSystemName="Race &amp; Ethnicity - CDC" displayName="White"/><!-- Additional Race --><sdtc:raceCode code="2108-9" codeSystem="2.16.840.1.113883.6.238" codeSystemName="Race &amp; Ethnicity - CDC" displayName="European"/><!-- Patient Ethnicity --><ethnicGroupCode nullFlavor="UNK"/><!-- Detailed Ethnicity --><sdtc:ethnicGroupCode nullFlavor="UNK"/><!-- Place of birth --><birthplace><place><addr><streetAddressLine nullFlavor="UNK"/><city nullFlavor="UNK"/><state nullFlavor="UNK"/><postalCode nullFlavor="UNK"/></addr></place></birthplace><languageCommunication><languageCode nullFlavor="UNK"/><!-- "Patient's preferred language" --><preferenceInd value="true"/></languageCommunication></patient><!-- Provider Organization --><providerOrganization><id nullFlavor="UNK"/><name nullFlavor="UNK"/><telecom nullFlavor="UNK"/><addr><streetAddressLine nullFlavor="UNK"/><city nullFlavor="UNK"/><state nullFlavor="UNK"/><postalCode nullFlavor="UNK"/></addr></providerOrganization></patientRole></recordTarget><!-- The author element represents the creator of the clinical document. The author may be a device or a person. CDA R2 requires that
author and author timestamp be asserted in the document header. From there, authorship propagates to contained sections and contained
entries, unless explicitly overridden.--><author><time value="20220507112334-0400"/><assignedAuthor><id root="1.3.6.1.4.1.24310"/><id nullFlavor="UNK" root="2.16.840.1.113883.4.6"/><addr use="WP"><streetAddressLine>1 Constitution Way</streetAddressLine><additionalLocator>Apt 2</additionalLocator><city>Foxboro</city><state>MA</state><postalCode>05158</postalCode><country>USA</country></addr><telecom use="WP" value="tel:+1(508)945-6522"/><assignedAuthoringDevice><manufacturerModelName>MEDITECH - Testing Release T5.6.7.MIS Interface Device</manufacturerModelName><softwareName>MEDITECH HCIS</softwareName></assignedAuthoringDevice><representedOrganization><id root="1.3.6.1.4.1.24310"/><name>Meditech Facility Author</name><telecom use="WP" value="tel:+1(508)945-6522"/><addr use="WP"><streetAddressLine>1 Constitution Way</streetAddressLine><additionalLocator>Apt 2</additionalLocator><city>Foxboro</city><state>MA</state><postalCode>05158</postalCode><country>USA</country></addr></representedOrganization></assignedAuthor></author><!-- The custodian element represents the organization that is in charge of maintaining and is entrusted with
the care of the document. --><custodian><assignedCustodian><representedCustodianOrganization><id root="1.3.6.1.4.1.24310"/><name>Dr Brenda Hill</name><telecom use="WP" value="tel:+1(508)947-5477"/><addr use="WP"><streetAddressLine>101 Martine St</streetAddressLine><additionalLocator>Suite 3</additionalLocator><city>Fall River</city><state>MA</state><postalCode>05125</postalCode><country>USA</country></addr></representedCustodianOrganization></assignedCustodian></custodian><!-- The participant represents supporting entities --><participant typeCode="IND"><!-- Indicates the start and end date of the relationship between the contact and the patient. --><time><low value="20220312"/></time><associatedEntity classCode="PRS"><code code="REFERREDXXX"><originalText>REFERRING</originalText></code><addr><streetAddressLine nullFlavor="UNK"/><city nullFlavor="UNK"/><state nullFlavor="UNK"/><postalCode nullFlavor="UNK"/></addr><associatedPerson><name><family>NOEL</family><given>AMANDA</given></name></associatedPerson></associatedEntity></participant><!-- The participant represents supporting entities --><participant typeCode="IND"><!-- Indicates the start and end date of the relationship between the contact and the patient. --><time><low value="20220312"/></time><associatedEntity classCode="PRS"><code code="FAMILYXXXXX"><originalText>FAMILY</originalText></code><addr><streetAddressLine nullFlavor="UNK"/><city nullFlavor="UNK"/><state nullFlavor="UNK"/><postalCode nullFlavor="UNK"/></addr><associatedPerson><name><family>PARLATO</family><given>AMANDA</given></name></associatedPerson></associatedEntity></participant><!-- The participant represents supporting entities --><participant typeCode="IND"><!-- Indicates the start and end date of the relationship between the contact and the patient. --><time><low value="20220312"/></time><associatedEntity classCode="PRS"><code code="OTHERXXXXXX"><originalText>OTHER</originalText></code><addr><streetAddressLine nullFlavor="UNK"/><city nullFlavor="UNK"/><state nullFlavor="UNK"/><postalCode nullFlavor="UNK"/></addr><associatedPerson><name><family>Roberts</family><given>Rickey</given></name></associatedPerson></associatedEntity></participant><!-- The participant represents supporting entities --><participant typeCode="IND"><!-- Indicates the start and end date of the relationship between the contact and the patient. --><time><low value="20220312"/></time><associatedEntity classCode="PRS"><code code="CONSULTINGX"><originalText>CONSULTING</originalText></code><addr><streetAddressLine nullFlavor="UNK"/><city nullFlavor="UNK"/><state nullFlavor="UNK"/><postalCode nullFlavor="UNK"/></addr><associatedPerson><name><family>Newton</family><given>Stephen</given></name></associatedPerson></associatedEntity></participant><componentOf><!-- The encompassingEncounter element records the specific encounter the document is detailing--><encompassingEncounter><id root="8589d447-a267-11ec-81e0-9e7eef92c510"/><id extension="0000016868" root="1.3.6.1.4.1.24310"/><code code="IMP" codeSystem="2.16.840.1.113883.5.4" codeSystemName="HL7 ActEncounterCode" displayName="inpatient encounter"/><effectiveTime><low value="20220312194500-0400"/></effectiveTime><dischargeDispositionCode nullFlavor="NA"/><responsibleParty><assignedEntity><id nullFlavor="UNK"/><code nullFlavor="UNK"/><addr><streetAddressLine nullFlavor="UNK"/><city nullFlavor="UNK"/><state nullFlavor="UNK"/><postalCode nullFlavor="UNK"/></addr><assignedPerson><name><family>MCUTLER</family></name></assignedPerson><representedOrganization><id root="2.25.216863694037274468345018764449062325569"/><name>CANTON MEDICAL CENTER OF MASSACHUSETTS-North Canton Facilit</name><telecom use="WP" value="tel:+1(781)821-3001"/><addr use="WP"><streetAddressLine>5001 North Mount Washington Circle Drive</streetAddressLine><additionalLocator>P.O. BOX 555566</additionalLocator><city>North Canton</city><state>MA</state><postalCode>02740-0001</postalCode><country>USA</country></addr></representedOrganization></assignedEntity></responsibleParty><encounterParticipant typeCode="REF"><assignedEntity><id extension="3583950233" root="2.16.840.1.113883.4.6"/><code nullFlavor="UNK"/><addr><streetAddressLine>2 COMMERCE DR</streetAddressLine><additionalLocator>UNIT #12</additionalLocator><city>BOSTON</city><state>MA</state><postalCode>11111</postalCode></addr><assignedPerson><name><family>Sher</family><given>Adam</given></name></assignedPerson><representedOrganization><id root="2.25.216863694037274468345018764449062325569"/><name>CANTON MEDICAL CENTER OF MASSACHUSETTS-North Canton Facilit</name><telecom use="WP" value="tel:+1(781)821-3001"/><addr use="WP"><streetAddressLine>5001 North Mount Washington Circle Drive</streetAddressLine><additionalLocator>P.O. BOX 555566</additionalLocator><city>North Canton</city><state>MA</state><postalCode>02740-0001</postalCode><country>USA</country></addr></representedOrganization></assignedEntity></encounterParticipant><encounterParticipant typeCode="REF"><assignedEntity><id extension="1234567893" root="2.16.840.1.113883.4.6"/><code nullFlavor="UNK"/><addr><streetAddressLine>20 ELM STREET</streetAddressLine><additionalLocator>SUITE 101 SECOND FLOOR NORTH</additionalLocator><city>BOSTON</city><state>MA</state><postalCode>02154</postalCode></addr><telecom use="HP" value="tel:+1(617)555-1234"/><assignedPerson><name><family>MEDITECH</family><given>DR</given></name></assignedPerson><representedOrganization><id root="2.25.216863694037274468345018764449062325569"/><name>CANTON MEDICAL CENTER OF MASSACHUSETTS-North Canton Facilit</name><telecom use="WP" value="tel:+1(781)821-3001"/><addr use="WP"><streetAddressLine>5001 North Mount Washington Circle Drive</streetAddressLine><additionalLocator>P.O. BOX 555566</additionalLocator><city>North Canton</city><state>MA</state><postalCode>02740-0001</postalCode><country>USA</country></addr></representedOrganization></assignedEntity></encounterParticipant><location><healthCareFacility><id root="7de7ddd5-ab3c-5fc4-925f-fd3ebc518e17"/><code code="GIM" codeSystem="2.16.840.1.113883.5.111" codeSystemName="RoleCode" displayName="General internal medicine clinic"/><location><addr use="WP"><streetAddressLine>1 Constitution Way</streetAddressLine><additionalLocator>Apt 2</additionalLocator><city>Foxboro</city><state>MA</state><postalCode>05158</postalCode><country>USA</country></addr></location><serviceProviderOrganization><name>Meditech Facility Author</name><telecom use="WP" value="tel:+1(508)945-6522"/><addr use="WP"><streetAddressLine>1 Constitution Way</streetAddressLine><additionalLocator>Apt 2</additionalLocator><city>Foxboro</city><state>MA</state><postalCode>05158</postalCode><country>USA</country></addr></serviceProviderOrganization></healthCareFacility></location></encompassingEncounter></componentOf><component><structuredBody><!-- Care Team CG21Apg5--><component><section><templateId extension="2019-07-01" root="2.16.840.1.113883.10.20.22.2.500"/><code code="85847-2" codeSystem="2.16.840.1.113883.6.1" codeSystemName="LOINC" displayName="Care team"/><title>Care Teams</title><text><content ID="careTeamName-1" styleCode="Bold">Patient Care Team</content><br/><table><thead><tr><th colspan="4">Team Status: Active</th></tr><tr><th>Member</th><th>Role</th><th>Status</th><th>Dates</th></tr></thead><tbody><tr><td>Adam Sher</td><td>admitting physician</td><td>Active</td><td>Start: March 12th, 2022<br/></td></tr><tr><td>MCUTLER</td><td>attending physician</td><td>Active</td><td>Start: March 12th, 2022<br/></td></tr><tr><td>DR MEDITECH</td><td>primary care physician</td><td>Active</td><td>Start: March 12th, 2022<br/></td></tr><tr><td>AMANDA NOEL</td><td>REFERRING</td><td>Active</td><td>Start: March 12th, 2022<br/></td></tr><tr><td>AMANDA PARLATO</td><td>FAMILY</td><td>Active</td><td>Start: March 12th, 2022<br/></td></tr><tr><td>Rickey Roberts</td><td>OTHER</td><td>Active</td><td>Start: March 12th, 2022<br/></td></tr><tr><td>Stephen Newton</td><td>CONSULTING</td><td>Active</td><td>Start: March 12th, 2022<br/></td></tr></tbody></table></text><entry><organizer classCode="CLUSTER" moodCode="EVN"><templateId extension="2019-08-01" root="2.16.840.1.113883.10.20.22.4.500"/><id root="8589d445-a267-11ec-81e0-9e7eef92c510"/><code code="86744-0" codeSystem="2.16.840.1.113883.6.1" codeSystemName="LOINC" displayName="Care Team"><originalText><reference value="#careTeamName-1"/></originalText></code><statusCode code="active"/><effectiveTime><low nullFlavor="UNK"/></effectiveTime><author><!-- Provenance - Author Participation --><templateId root="2.16.840.1.113883.10.20.22.4.119"/><templateId extension="2019-10-01" root="2.16.840.1.113883.10.20.22.5.6"/><time value="20220312184600-0500"/><assignedAuthor><!-- NPI of Author --><id extension="1111111112" root="2.16.840.1.113883.4.6"/><assignedPerson><name><family>MEDITECH</family><given>ALI</given></name></assignedPerson><representedOrganization><!-- NPI of Organization --><id nullFlavor="UNK" root="2.16.840.1.113883.4.6"/><name>CANTON MEDICAL CENTER OF MASSACHUSETTS-North Canton Facilit</name><telecom use="WP" value="tel:+1(781)821-3001"/></representedOrganization></assignedAuthor></author><!-- Care Team Members --><component><act classCode="PCPR" moodCode="EVN"><templateId extension="2019-07-01" root="2.16.840.1.113883.10.20.22.4.500.1"/><id root="b3b93188-29ee-567e-8216-30f4d3c8e283"/><code code="85847-2" codeSystem="2.16.840.1.113883.6.1" codeSystemName="LOINC" displayName="Care Team Information"/><statusCode code="active"/><effectiveTime><low value="20220312"/></effectiveTime><performer typeCode="PRF"><sdtc:functionCode nullFlavor="UNK"><originalText>admitting physician</originalText></sdtc:functionCode><assignedEntity><id root="b3b93188-29ee-567e-8216-30f4d3c8e283"/><addr><streetAddressLine>2 COMMERCE DR</streetAddressLine><additionalLocator>UNIT #12</additionalLocator><city>BOSTON</city><state>MA</state><postalCode>11111</postalCode></addr><assignedPerson><name><family>Sher</family><given>Adam</given></name></assignedPerson></assignedEntity></performer></act></component><component><act classCode="PCPR" moodCode="EVN"><templateId extension="2019-07-01" root="2.16.840.1.113883.10.20.22.4.500.1"/><id root="090567dd-7557-53f7-a112-4c512a7df461"/><code code="85847-2" codeSystem="2.16.840.1.113883.6.1" codeSystemName="LOINC" displayName="Care Team Information"/><statusCode code="active"/><effectiveTime><low value="20220312"/></effectiveTime><performer typeCode="PRF"><sdtc:functionCode nullFlavor="UNK"><originalText>attending physician</originalText></sdtc:functionCode><assignedEntity><id root="090567dd-7557-53f7-a112-4c512a7df461"/><addr><streetAddressLine nullFlavor="UNK"/><city nullFlavor="UNK"/><state nullFlavor="UNK"/><postalCode nullFlavor="UNK"/></addr><assignedPerson><name><family>MCUTLER</family></name></assignedPerson></assignedEntity></performer></act></component><component><act classCode="PCPR" moodCode="EVN"><templateId extension="2019-07-01" root="2.16.840.1.113883.10.20.22.4.500.1"/><id root="362f07a0-c8bc-5023-837d-524a9c74cc60"/><code code="85847-2" codeSystem="2.16.840.1.113883.6.1" codeSystemName="LOINC" displayName="Care Team Information"/><statusCode code="active"/><effectiveTime><low value="20220312"/></effectiveTime><performer typeCode="PRF"><sdtc:functionCode nullFlavor="UNK"><originalText>primary care physician</originalText></sdtc:functionCode><assignedEntity><id root="362f07a0-c8bc-5023-837d-524a9c74cc60"/><addr><streetAddressLine>20 ELM STREET</streetAddressLine><additionalLocator>SUITE 101 SECOND FLOOR NORTH</additionalLocator><city>BOSTON</city><state>MA</state><postalCode>02154</postalCode></addr><telecom use="WP" value="tel:+1(617)555-1234"/><assignedPerson><name><family>MEDITECH</family><given>DR</given></name></assignedPerson></assignedEntity></performer></act></component><component><act classCode="PCPR" moodCode="EVN"><templateId extension="2019-07-01" root="2.16.840.1.113883.10.20.22.4.500.1"/><id root="8071c21f-89ed-5614-ac47-7d564a56fe75"/><code code="85847-2" codeSystem="2.16.840.1.113883.6.1" codeSystemName="LOINC" displayName="Care Team Information"/><statusCode code="active"/><effectiveTime><low value="20220312"/></effectiveTime><performer typeCode="PRF"><sdtc:functionCode nullFlavor="UNK"><originalText>REFERRING</originalText></sdtc:functionCode><assignedEntity><id root="8071c21f-89ed-5614-ac47-7d564a56fe75"/><addr><streetAddressLine nullFlavor="UNK"/><city nullFlavor="UNK"/><state nullFlavor="UNK"/><postalCode nullFlavor="UNK"/></addr><assignedPerson><name><family>NOEL</family><given>AMANDA</given></name></assignedPerson></assignedEntity></performer></act></component><component><act classCode="PCPR" moodCode="EVN"><templateId extension="2019-07-01" root="2.16.840.1.113883.10.20.22.4.500.1"/><id root="5751a12b-e49b-4749-9ff1-0bcbf4cac19d"/><code code="85847-2" codeSystem="2.16.840.1.113883.6.1" codeSystemName="LOINC" displayName="Care Team Information"/><statusCode code="active"/><effectiveTime><low value="20220312"/></effectiveTime><performer typeCode="PRF"><sdtc:functionCode nullFlavor="UNK"><originalText>FAMILY</originalText></sdtc:functionCode><assignedEntity><id root="5751a12b-e49b-4749-9ff1-0bcbf4cac19d"/><addr><streetAddressLine nullFlavor="UNK"/><city nullFlavor="UNK"/><state nullFlavor="UNK"/><postalCode nullFlavor="UNK"/></addr><assignedPerson><name><family>PARLATO</family><given>AMANDA</given></name></assignedPerson></assignedEntity></performer></act></component><component><act classCode="PCPR" moodCode="EVN"><templateId extension="2019-07-01" root="2.16.840.1.113883.10.20.22.4.500.1"/><id root="8b8515df-ec5c-56e3-85b1-fb812ad54a60"/><code code="85847-2" codeSystem="2.16.840.1.113883.6.1" codeSystemName="LOINC" displayName="Care Team Information"/><statusCode code="active"/><effectiveTime><low value="20220312"/></effectiveTime><performer typeCode="PRF"><sdtc:functionCode nullFlavor="UNK"><originalText>OTHER</originalText></sdtc:functionCode><assignedEntity><id root="8b8515df-ec5c-56e3-85b1-fb812ad54a60"/><addr><streetAddressLine nullFlavor="UNK"/><city nullFlavor="UNK"/><state nullFlavor="UNK"/><postalCode nullFlavor="UNK"/></addr><assignedPerson><name><family>Roberts</family><given>Rickey</given></name></assignedPerson></assignedEntity></performer></act></component><component><act classCode="PCPR" moodCode="EVN"><templateId extension="2019-07-01" root="2.16.840.1.113883.10.20.22.4.500.1"/><id root="14570e4d-f500-55c6-9d8a-5aa496f7e3dc"/><code code="85847-2" codeSystem="2.16.840.1.113883.6.1" codeSystemName="LOINC" displayName="Care Team Information"/><statusCode code="active"/><effectiveTime><low value="20220312"/></effectiveTime><performer typeCode="PRF"><sdtc:functionCode nullFlavor="UNK"><originalText>CONSULTING</originalText></sdtc:functionCode><assignedEntity><id root="14570e4d-f500-55c6-9d8a-5aa496f7e3dc"/><addr><streetAddressLine nullFlavor="UNK"/><city nullFlavor="UNK"/><state nullFlavor="UNK"/><postalCode nullFlavor="UNK"/></addr><assignedPerson><name><family>Newton</family><given>Stephen</given></name></assignedPerson></assignedEntity></performer></act></component></organizer></entry></section></component><!-- Reason for Visit Section eCR IGpg 106 --><component><section><templateId root="2.16.840.1.113883.10.20.22.2.12"/><code code="29299-5" codeSystem="2.16.840.1.113883.6.1" codeSystemName="LOINC" displayName="Reason for Visit"/><title>Reason for Visit</title><text>No reason for visit information available</text></section></component><!-- History of Present Illness Section IGpg310 --><component><section nullFlavor="NI"><templateId root="1.3.6.1.4.1.19376.1.5.3.1.3.4"/><code code="10164-2" codeSystem="2.16.840.1.113883.6.1" codeSystemName="LOINC" displayName="History Of Present Illness"/><title>History of Present Illness</title><text>No history of present illness information available</text></section></component><!-- Social History Section (V3) IGpg404 --><component><section><templateId extension="2015-08-01" root="2.16.840.1.113883.10.20.22.2.17"/><templateId root="2.16.840.1.113883.10.20.22.2.17"/><code code="29762-2" codeSystem="2.16.840.1.113883.6.1" codeSystemName="LOINC" displayName="Social History"/><title>Social History</title><text><content styleCode="Bold">Smoking Status</content><br/><content>Unknown if ever smoked</content><br/><content styleCode="Bold">Additional Data</content><br/><table><tbody><tr><th>Assigned Birth Sex</th><td ID="birthsex">Male</td></tr><tr><th>Gender Identity</th><td ID="gender-identity">unknown</td></tr><tr><th>Sexual Orientation</th><td ID="sexual-orientation">Do not know</td></tr></tbody></table></text><!-- Smoking Status - Meaningful Use (V2) IGpg834 --><entry><observation classCode="OBS" moodCode="EVN"><templateId extension="2014-06-09" root="2.16.840.1.113883.10.20.22.4.78"/><templateId root="2.16.840.1.113883.10.20.22.4.78"/><id root="bc4574c5-e6ab-4ac2-8c17-f538dec91e5f"/><code code="72166-2" codeSystem="2.16.840.1.113883.6.1" displayName="Tobacco smoking status NHIS"/><statusCode code="completed"/><!-- The effectiveTime reflects when the current smoking status was observed. --><effectiveTime nullFlavor="UNK"/><!-- The value represents the patient's smoking status currently observed. --><value code="266927001" codeSystem="2.16.840.1.113883.6.96" displayName="Unknown if ever smoked" xsi:type="CD"/></observation></entry><!-- Birth Sex Observation CDA21CCIGpg85 --><entry><observation classCode="OBS" moodCode="EVN"><templateId extension="2016-06-01" root="2.16.840.1.113883.10.20.22.4.200"/><id root="5b3ca52b-0d5b-4131-a961-f74bffb7451e"/><code code="76689-9" codeSystem="2.16.840.1.113883.6.1" displayName="Sex Assigned At Birth"/><statusCode code="completed"/><effectiveTime value="19600912"/><value code="M" codeSystem="2.16.840.1.113883.5.1" codeSystemName="AdministrativeGender" displayName="Male" xsi:type="CD"><originalText><reference value="#birthsex"/></originalText></value><author><!-- Provenance - Author Participation --><templateId root="2.16.840.1.113883.10.20.22.4.119"/><templateId extension="2019-10-01" root="2.16.840.1.113883.10.20.22.5.6"/><time value="20220324110700-0400"/><assignedAuthor><!-- NPI of Author --><id nullFlavor="UNK" root="2.16.840.1.113883.4.6"/><representedOrganization><!-- NPI of Organization --><id extension="9390001110" root="2.16.840.1.113883.4.6"/><name>Meditech Facility Author</name><telecom use="WP" value="tel:+1(508)945-6522"/></representedOrganization></assignedAuthor></author></observation></entry><!-- Gender Identity Observation CDA21CGpg174 --><entry><observation classCode="OBS" moodCode="EVN"><templateId extension="2015-08-01" root="2.16.840.1.113883.10.20.22.4.38"/><templateId root="2.16.840.1.113883.10.20.22.4.38"/><id root="e11c245b-68f9-4d76-88c6-e419340a61fa"/><code code="76691-5" codeSystem="2.16.840.1.113883.6.1" displayName="Gender Identity"/><statusCode code="completed"/><effectiveTime xsi:type="IVL_TS"><low nullFlavor="UNK"/></effectiveTime><value nullFlavor="UNK" xsi:type="CD"><originalText><reference value="#gender-identity"/></originalText></value></observation></entry><!-- Sexual Orientation Observation CDA21CGpg174 --><entry><observation classCode="OBS" moodCode="EVN"><templateId extension="2015-08-01" root="2.16.840.1.113883.10.20.22.4.38"/><templateId root="2.16.840.1.113883.10.20.22.4.38"/><id root="05ee7516-23c7-4f0e-8a35-95bf35a8b6ea"/><code code="76690-7" codeSystem="2.16.840.1.113883.6.1" displayName="Sexual Orientation"/><statusCode code="completed"/><effectiveTime xsi:type="IVL_TS"><low nullFlavor="UNK"/></effectiveTime><value nullFlavor="UNK" xsi:type="CD"><originalText><reference value="#sexual-orientation"/></originalText></value></observation></entry></section></component><component><section><!-- Problem Section (entries required) (V3) [section: identifier urn:hl7ii:2.16.840.1.113883.10.20.22.2.5.1:2015-08-01 IGpg371--><templateId extension="2015-08-01" root="2.16.840.1.113883.10.20.22.2.5.1"/><templateId root="2.16.840.1.113883.10.20.22.2.5.1"/><code code="11450-4" codeSystem="2.16.840.1.113883.6.1" codeSystemName="LOINC" displayName="PROBLEM LIST"/><title>Problems</title><text><content styleCode="Bold">Active Problems</content><br/><table><thead><tr><th>Medical Problem</th><th>Onset Date</th><th>Status</th></tr></thead><tbody><tr><td ID="problem-1">Anthrax</td><td/><td>Active</td></tr><tr><td ID="problem-2">COVID-19</td><td/><td>Active</td></tr></tbody></table></text><entry typeCode="DRIV"><!-- Problem Concern Act (V3) [act: identifier urn:hl7ii:2.16.840.1.113883.10.20.22.4.3:2015-08-01 IGpg732 --><act classCode="ACT" moodCode="EVN"><templateId extension="2015-08-01" root="2.16.840.1.113883.10.20.22.4.3"/><templateId root="2.16.840.1.113883.10.20.22.4.3"/><id root="a2cd44d9-ab84-11ec-81e0-9e7eef92c510"/><code code="CONC" codeSystem="2.16.840.1.113883.5.6" codeSystemName="HL7 ActClass" displayName="Concern"/><!-- The statusCode represents the need to continue tracking the problem --><!-- This is of ongoing concern to the provider --><statusCode code="active"/><!-- "The low value represents when the problem was first recorded in the patient's chart" --><effectiveTime><low value="20220324110500-0400"/></effectiveTime><entryRelationship typeCode="SUBJ"><!-- Problem observation (V3) observation: identifier urn:hl7ii:2.16.840.1.113883.10.20.22.4.4:2015-08-01 IGpg737--><observation classCode="OBS" moodCode="EVN" negationInd="false"><templateId extension="2015-08-01" root="2.16.840.1.113883.10.20.22.4.4"/><templateId root="2.16.840.1.113883.10.20.22.4.4"/><!-- eICR R2 STU1.1 Initial Case Report Trigger Code Problem Observation IGpg187--><templateId extension="2016-12-01" root="2.16.840.1.113883.10.20.15.2.3.3"/><id root="5dd0f7f1-ffc0-4447-9c8c-66b7adc6bf28"/><code code="55607006" codeSystem="2.16.840.1.113883.6.96" codeSystemName="SNOMED-CT" displayName="Problem"><!-- a.	This code SHALL contain at least one [1..*] translation, which SHOULD be selected from ValueSet Problem Type (LOINC)--><translation code="75326-9" codeSystem="2.16.840.1.113883.6.1" codeSystemName="LOINC" displayName="Problem"/></code><!-- The statusCode reflects the status of the observation itself --><statusCode code="completed"/><effectiveTime><low nullFlavor="UNK"/></effectiveTime><value code="409498004" codeSystem="2.16.840.1.113883.6.96" codeSystemName="SNOMED CT" displayName="Anthrax" xsi:type="CD"><originalText><reference value="#problem-1"/></originalText><translation code="022.9" codeSystem="2.16.840.1.113883.6.103" codeSystemName="ICD9" displayName="Anthrax"/><translation code="A22.9" codeSystem="2.16.840.1.113883.6.90" codeSystemName="ICD10" displayName="Anthrax" sdtc:valueSet="2.16.840.1.114222.4.11.7508" sdtc:valueSetVersion="2022-01-12"/></value><author><!-- Provenance - Author Participation --><templateId root="2.16.840.1.113883.10.20.22.4.119"/><templateId extension="2019-10-01" root="2.16.840.1.113883.10.20.22.5.6"/><time value="20220324110500-0400"/><assignedAuthor><!-- NPI of Author --><id extension="1111111112" root="2.16.840.1.113883.4.6"/><assignedPerson><name><family>MEDITECH</family><given>ALI</given></name></assignedPerson><representedOrganization><!-- NPI of Organization --><id nullFlavor="UNK" root="2.16.840.1.113883.4.6"/><name>CANTON MEDICAL CENTER OF MASSACHUSETTS-North Canton Facilit</name><telecom use="WP" value="tel:+1(781)821-3001"/></representedOrganization></assignedAuthor></author></observation></entryRelationship></act></entry><entry typeCode="DRIV"><!-- Problem Concern Act (V3) [act: identifier urn:hl7ii:2.16.840.1.113883.10.20.22.4.3:2015-08-01 IGpg732 --><act classCode="ACT" moodCode="EVN"><templateId extension="2015-08-01" root="2.16.840.1.113883.10.20.22.4.3"/><templateId root="2.16.840.1.113883.10.20.22.4.3"/><id root="a2cd44da-ab84-11ec-81e0-9e7eef92c510"/><code code="CONC" codeSystem="2.16.840.1.113883.5.6" codeSystemName="HL7 ActClass" displayName="Concern"/><!-- The statusCode represents the need to continue tracking the problem --><!-- This is of ongoing concern to the provider --><statusCode code="active"/><!-- "The low value represents when the problem was first recorded in the patient's chart" --><effectiveTime><low value="20220324110600-0400"/></effectiveTime><entryRelationship typeCode="SUBJ"><!-- Problem observation (V3) observation: identifier urn:hl7ii:2.16.840.1.113883.10.20.22.4.4:2015-08-01 IGpg737--><observation classCode="OBS" moodCode="EVN" negationInd="false"><templateId extension="2015-08-01" root="2.16.840.1.113883.10.20.22.4.4"/><templateId root="2.16.840.1.113883.10.20.22.4.4"/><!-- eICR R2 STU1.1 Initial Case Report Trigger Code Problem Observation IGpg187--><templateId extension="2016-12-01" root="2.16.840.1.113883.10.20.15.2.3.3"/><id root="f12fc3b2-0685-4ba0-930f-bac0d26a4c70"/><code code="55607006" codeSystem="2.16.840.1.113883.6.96" codeSystemName="SNOMED-CT" displayName="Problem"><!-- a.	This code SHALL contain at least one [1..*] translation, which SHOULD be selected from ValueSet Problem Type (LOINC)--><translation code="75326-9" codeSystem="2.16.840.1.113883.6.1" codeSystemName="LOINC" displayName="Problem"/></code><!-- The statusCode reflects the status of the observation itself --><statusCode code="completed"/><effectiveTime><low nullFlavor="UNK"/></effectiveTime><value code="840539006" codeSystem="2.16.840.1.113883.6.96" codeSystemName="SNOMED CT" displayName="Infection due to severe acute respiratory syndrome coronavirus 2 (SARS-CoV-2)" xsi:type="CD"><originalText><reference value="#problem-2"/></originalText><translation code="079.89" codeSystem="2.16.840.1.113883.6.103" codeSystemName="ICD9" displayName="Infection due to severe acute respiratory syndrome coronavirus 2 (SARS-CoV-2)"/><translation code="U07.1" codeSystem="2.16.840.1.113883.6.90" codeSystemName="ICD10" displayName="Infection due to severe acute respiratory syndrome coronavirus 2 (SARS-CoV-2)" sdtc:valueSet="2.16.840.1.114222.4.11.7508" sdtc:valueSetVersion="2022-01-12"/></value><author><!-- Provenance - Author Participation --><templateId root="2.16.840.1.113883.10.20.22.4.119"/><templateId extension="2019-10-01" root="2.16.840.1.113883.10.20.22.5.6"/><time value="20220324110600-0400"/><assignedAuthor><!-- NPI of Author --><id extension="1111111112" root="2.16.840.1.113883.4.6"/><assignedPerson><name><family>MEDITECH</family><given>ALI</given></name></assignedPerson><representedOrganization><!-- NPI of Organization --><id nullFlavor="UNK" root="2.16.840.1.113883.4.6"/><name>CANTON MEDICAL CENTER OF MASSACHUSETTS-North Canton Facilit</name><telecom use="WP" value="tel:+1(781)821-3001"/></representedOrganization></assignedAuthor></author></observation></entryRelationship></act></entry></section></component><component><section><!-- Immunizations section IGpg320 --><templateId extension="2015-08-01" root="2.16.840.1.113883.10.20.22.2.2.1"/><templateId root="2.16.840.1.113883.10.20.22.2.2.1"/><templateId root="2.16.840.1.113883.10.20.22.2.2"/><code code="11369-6" codeSystem="2.16.840.1.113883.6.1" codeSystemName="LOINC" displayName="History of immunizations"/><title>Immunizations</title><text><table><thead><tr><th>Immunization</th><th>Event Date</th><th>Not Given Reason</th><th>Dose Number</th><th>Manufacturer</th><th>Lot Number</th><th>Vaccine Information Statement (VIS) Detail</th></tr></thead><tbody><tr><td ID="immun-1">Date patient received Moderna COVID-19 vaccine?</td><td/><td/><td/><td/><td/><td/></tr><tr><td ID="immun-2">Date patient received Anthrax vaccine?</td><td/><td/><td/><td/><td/><td/></tr><tr><td ID="immun-3">Date patient received Rabies vaccine?</td><td/><td/><td/><td/><td/><td/></tr><tr><td ID="immun-4">anthrax</td><td>March 15th, 2022 7:20am</td><td/><td>1</td><td>PFIZER &amp; OTHER CHARACTERS</td><td>LOT9911Z</td><td/></tr><tr><td ID="immun-5">RIG</td><td/><td ID="immun-refRea5">RAPID HEART BEAT</td><td/><td/><td/><td/></tr><tr><td ID="immun-6">anthrax</td><td>March 24th, 2022 9:34am</td><td/><td>2</td><td>JOHNSON AND JOHNSON</td><td>LOT942X</td><td/></tr></tbody></table></text><entry typeCode="DRIV"><substanceAdministration classCode="SBADM" moodCode="EVN" negationInd="false"><!-- Immunization Activity (V3) IGpg551 --><templateId extension="2015-08-01" root="2.16.840.1.113883.10.20.22.4.52"/><templateId root="2.16.840.1.113883.10.20.22.4.52"/><id root="f388d4f6-a451-11ec-81e0-9e7eef92c510"/><statusCode code="completed"/><effectiveTime nullFlavor="UNK"/><routeCode nullFlavor="UNK"/><approachSiteCode nullFlavor="UNK"/><consumable><manufacturedProduct classCode="MANU"><!-- Immunization Medication Information IGpg563 --><templateId extension="2014-06-09" root="2.16.840.1.113883.10.20.22.4.54"/><templateId root="2.16.840.1.113883.10.20.22.4.54"/><manufacturedMaterial><code nullFlavor="UNK"><originalText><reference value="#immun-1"/></originalText></code><lotNumberText nullFlavor="UNK"/></manufacturedMaterial><manufacturerOrganization><name/></manufacturerOrganization></manufacturedProduct></consumable><!-- Drug vehicle IGpg478--><participant typeCode="CSM"><participantRole classCode="MANU"><templateId root="2.16.840.1.113883.10.20.22.4.24"/><code code="412307009" codeSystem="2.16.840.1.113883.6.96" displayName="Drug vehicle"/><playingEntity classCode="MMAT"><code nullFlavor="UNK"/><name/></playingEntity></participantRole></participant><!-- Indication - Reason for medication IGpg570 --><entryRelationship typeCode="RSON"><observation classCode="OBS" moodCode="EVN"><templateId extension="2014-06-09" root="2.16.840.1.113883.10.20.22.4.19"/><templateId root="2.16.840.1.113883.10.20.22.4.19"/><id nullFlavor="NA"/><code code="ASSERTION" codeSystem="2.16.840.1.113883.5.4"/><statusCode code="completed"/><value nullFlavor="UNK" xsi:type="CD"/></observation></entryRelationship></substanceAdministration></entry><entry typeCode="DRIV"><substanceAdministration classCode="SBADM" moodCode="EVN" negationInd="false"><!-- Immunization Activity (V3) IGpg551 --><templateId extension="2015-08-01" root="2.16.840.1.113883.10.20.22.4.52"/><templateId root="2.16.840.1.113883.10.20.22.4.52"/><id root="f388d4f7-a451-11ec-81e0-9e7eef92c510"/><statusCode code="completed"/><effectiveTime nullFlavor="UNK"/><routeCode nullFlavor="UNK"/><approachSiteCode nullFlavor="UNK"/><consumable><manufacturedProduct classCode="MANU"><!-- Immunization Medication Information IGpg563 --><templateId extension="2014-06-09" root="2.16.840.1.113883.10.20.22.4.54"/><templateId root="2.16.840.1.113883.10.20.22.4.54"/><manufacturedMaterial><code nullFlavor="UNK"><originalText><reference value="#immun-2"/></originalText></code><lotNumberText nullFlavor="UNK"/></manufacturedMaterial><manufacturerOrganization><name/></manufacturerOrganization></manufacturedProduct></consumable><!-- Drug vehicle IGpg478--><participant typeCode="CSM"><participantRole classCode="MANU"><templateId root="2.16.840.1.113883.10.20.22.4.24"/><code code="412307009" codeSystem="2.16.840.1.113883.6.96" displayName="Drug vehicle"/><playingEntity classCode="MMAT"><code nullFlavor="UNK"/><name/></playingEntity></participantRole></participant><!-- Indication - Reason for medication IGpg570 --><entryRelationship typeCode="RSON"><observation classCode="OBS" moodCode="EVN"><templateId extension="2014-06-09" root="2.16.840.1.113883.10.20.22.4.19"/><templateId root="2.16.840.1.113883.10.20.22.4.19"/><id nullFlavor="NA"/><code code="ASSERTION" codeSystem="2.16.840.1.113883.5.4"/><statusCode code="completed"/><value nullFlavor="UNK" xsi:type="CD"/></observation></entryRelationship></substanceAdministration></entry><entry typeCode="DRIV"><substanceAdministration classCode="SBADM" moodCode="EVN" negationInd="false"><!-- Immunization Activity (V3) IGpg551 --><templateId extension="2015-08-01" root="2.16.840.1.113883.10.20.22.4.52"/><templateId root="2.16.840.1.113883.10.20.22.4.52"/><id root="f388d4f8-a451-11ec-81e0-9e7eef92c510"/><statusCode code="completed"/><effectiveTime nullFlavor="UNK"/><routeCode nullFlavor="UNK"/><approachSiteCode nullFlavor="UNK"/><consumable><manufacturedProduct classCode="MANU"><!-- Immunization Medication Information IGpg563 --><templateId extension="2014-06-09" root="2.16.840.1.113883.10.20.22.4.54"/><templateId root="2.16.840.1.113883.10.20.22.4.54"/><manufacturedMaterial><code nullFlavor="UNK"><originalText><reference value="#immun-3"/></originalText></code><lotNumberText nullFlavor="UNK"/></manufacturedMaterial><manufacturerOrganization><name/></manufacturerOrganization></manufacturedProduct></consumable><!-- Drug vehicle IGpg478--><participant typeCode="CSM"><participantRole classCode="MANU"><templateId root="2.16.840.1.113883.10.20.22.4.24"/><code code="412307009" codeSystem="2.16.840.1.113883.6.96" displayName="Drug vehicle"/><playingEntity classCode="MMAT"><code nullFlavor="UNK"/><name/></playingEntity></participantRole></participant><!-- Indication - Reason for medication IGpg570 --><entryRelationship typeCode="RSON"><observation classCode="OBS" moodCode="EVN"><templateId extension="2014-06-09" root="2.16.840.1.113883.10.20.22.4.19"/><templateId root="2.16.840.1.113883.10.20.22.4.19"/><id nullFlavor="NA"/><code code="ASSERTION" codeSystem="2.16.840.1.113883.5.4"/><statusCode code="completed"/><value nullFlavor="UNK" xsi:type="CD"/></observation></entryRelationship></substanceAdministration></entry><entry typeCode="DRIV"><substanceAdministration classCode="SBADM" moodCode="EVN" negationInd="false"><!-- Immunization Activity (V3) IGpg551 --><templateId extension="2015-08-01" root="2.16.840.1.113883.10.20.22.4.52"/><templateId root="2.16.840.1.113883.10.20.22.4.52"/><id root="f388d4f9-a451-11ec-81e0-9e7eef92c510"/><statusCode code="completed"/><effectiveTime value="20220315072000-0400"/><routeCode nullFlavor="UNK"/><approachSiteCode nullFlavor="UNK"/><consumable><manufacturedProduct classCode="MANU"><!-- Immunization Medication Information IGpg563 --><templateId extension="2014-06-09" root="2.16.840.1.113883.10.20.22.4.54"/><templateId root="2.16.840.1.113883.10.20.22.4.54"/><manufacturedMaterial><code code="24" codeSystem="2.16.840.1.113883.12.292" codeSystemName="CVX" displayName="anthrax"><originalText><reference value="#immun-4"/></originalText></code><lotNumberText>LOT9911Z</lotNumberText></manufacturedMaterial><manufacturerOrganization><name>PFIZER &amp; OTHER CHARACTERS</name></manufacturerOrganization></manufacturedProduct></consumable><author><!-- Provenance - Author Participation --><templateId root="2.16.840.1.113883.10.20.22.4.119"/><templateId extension="2019-10-01" root="2.16.840.1.113883.10.20.22.5.6"/><time value="20220315072000-0400"/><assignedAuthor><!-- NPI of Author --><id extension="1111111112" root="2.16.840.1.113883.4.6"/><assignedPerson><name><family>MEDITECH</family><given>ALI</given></name></assignedPerson><representedOrganization><!-- NPI of Organization --><id nullFlavor="UNK" root="2.16.840.1.113883.4.6"/><name>CANTON MEDICAL CENTER OF MASSACHUSETTS-North Canton Facilit</name><telecom use="WP" value="tel:+1(781)821-3001"/></representedOrganization></assignedAuthor></author><!-- Drug vehicle IGpg478--><participant typeCode="CSM"><participantRole classCode="MANU"><templateId root="2.16.840.1.113883.10.20.22.4.24"/><code code="412307009" codeSystem="2.16.840.1.113883.6.96" displayName="Drug vehicle"/><playingEntity classCode="MMAT"><code nullFlavor="UNK"/><name/></playingEntity></participantRole></participant><!-- Indication - Reason for medication IGpg570 --><entryRelationship typeCode="RSON"><observation classCode="OBS" moodCode="EVN"><templateId extension="2014-06-09" root="2.16.840.1.113883.10.20.22.4.19"/><templateId root="2.16.840.1.113883.10.20.22.4.19"/><id nullFlavor="NA"/><code code="ASSERTION" codeSystem="2.16.840.1.113883.5.4"/><statusCode code="completed"/><value nullFlavor="UNK" xsi:type="CD"/></observation></entryRelationship><entryRelationship inversionInd="true" typeCode="COMP"><!-- Sequence in administration series --><sequenceNumber value="1"/><!-- Substance Administered Act IGpg847 --><act classCode="ACT" moodCode="EVN"><templateId root="2.16.840.1.113883.10.20.22.4.118"/><id root="0720636d-2fb9-4d4f-bfd6-add6bda4f7b0"/><code code="416118004" codeSystem="2.16.840.1.113883.6.96" codeSystemName="SNOMED CT" displayName="Administration"/><statusCode code="completed"/><effectiveTime value="20220315072000-0400"/></act></entryRelationship></substanceAdministration></entry><entry typeCode="DRIV"><substanceAdministration classCode="SBADM" moodCode="EVN" negationInd="true"><!-- Immunization Activity (V3) IGpg551 --><templateId extension="2015-08-01" root="2.16.840.1.113883.10.20.22.4.52"/><templateId root="2.16.840.1.113883.10.20.22.4.52"/><id root="8bdb0ffa-a9d2-11ec-81e0-9e7eef92c510"/><statusCode code="completed"/><effectiveTime nullFlavor="UNK"/><routeCode nullFlavor="UNK"/><approachSiteCode nullFlavor="UNK"/><consumable><manufacturedProduct classCode="MANU"><!-- Immunization Medication Information IGpg563 --><templateId extension="2014-06-09" root="2.16.840.1.113883.10.20.22.4.54"/><templateId root="2.16.840.1.113883.10.20.22.4.54"/><manufacturedMaterial><code code="34" codeSystem="2.16.840.1.113883.12.292" codeSystemName="CVX" displayName="RIG"><originalText><reference value="#immun-5"/></originalText></code><lotNumberText nullFlavor="UNK"/></manufacturedMaterial><manufacturerOrganization><name/></manufacturerOrganization></manufacturedProduct></consumable><author><!-- Provenance - Author Participation --><templateId root="2.16.840.1.113883.10.20.22.4.119"/><templateId extension="2019-10-01" root="2.16.840.1.113883.10.20.22.5.6"/><time value="20220315073000-0400"/><assignedAuthor><!-- NPI of Author --><id extension="1111111112" root="2.16.840.1.113883.4.6"/><assignedPerson><name><family>MEDITECH</family><given>ALI</given></name></assignedPerson><representedOrganization><!-- NPI of Organization --><id nullFlavor="UNK" root="2.16.840.1.113883.4.6"/><name>CANTON MEDICAL CENTER OF MASSACHUSETTS-North Canton Facilit</name><telecom use="WP" value="tel:+1(781)821-3001"/></representedOrganization></assignedAuthor></author><!-- Drug vehicle IGpg478--><participant typeCode="CSM"><participantRole classCode="MANU"><templateId root="2.16.840.1.113883.10.20.22.4.24"/><code code="412307009" codeSystem="2.16.840.1.113883.6.96" displayName="Drug vehicle"/><playingEntity classCode="MMAT"><code nullFlavor="UNK"/><name/></playingEntity></participantRole></participant><entryRelationship typeCode="RSON"><observation classCode="OBS" moodCode="EVN"><!-- Immunization Refusal Reason  --><templateId root="2.16.840.1.113883.10.20.22.4.53"/><id root="532be90e-7b24-4d53-b678-ab4cf995dec8"/><code nullFlavor="UNK"><originalText><reference value="#immun-refRea-5"/></originalText></code><statusCode code="completed"/></observation></entryRelationship><!-- Indication - Reason for medication IGpg570 --><entryRelationship typeCode="RSON"><observation classCode="OBS" moodCode="EVN"><templateId extension="2014-06-09" root="2.16.840.1.113883.10.20.22.4.19"/><templateId root="2.16.840.1.113883.10.20.22.4.19"/><id nullFlavor="NA"/><code code="ASSERTION" codeSystem="2.16.840.1.113883.5.4"/><statusCode code="completed"/><value nullFlavor="UNK" xsi:type="CD"/></observation></entryRelationship></substanceAdministration></entry><entry typeCode="DRIV"><substanceAdministration classCode="SBADM" moodCode="EVN" negationInd="false"><!-- Immunization Activity (V3) IGpg551 --><templateId extension="2015-08-01" root="2.16.840.1.113883.10.20.22.4.52"/><templateId root="2.16.840.1.113883.10.20.22.4.52"/><id root="66d08d45-ab7b-11ec-81e0-9e7eef92c510"/><statusCode code="completed"/><effectiveTime value="20220324093400-0400"/><routeCode nullFlavor="UNK"/><approachSiteCode nullFlavor="UNK"/><consumable><manufacturedProduct classCode="MANU"><!-- Immunization Medication Information IGpg563 --><templateId extension="2014-06-09" root="2.16.840.1.113883.10.20.22.4.54"/><templateId root="2.16.840.1.113883.10.20.22.4.54"/><manufacturedMaterial><code code="24" codeSystem="2.16.840.1.113883.12.292" codeSystemName="CVX" displayName="anthrax"><originalText><reference value="#immun-6"/></originalText></code><lotNumberText>LOT942X</lotNumberText></manufacturedMaterial><manufacturerOrganization><name>JOHNSON AND JOHNSON</name></manufacturerOrganization></manufacturedProduct></consumable><author><!-- Provenance - Author Participation --><templateId root="2.16.840.1.113883.10.20.22.4.119"/><templateId extension="2019-10-01" root="2.16.840.1.113883.10.20.22.5.6"/><time value="20220324093500-0400"/><assignedAuthor><!-- NPI of Author --><id extension="1111111112" root="2.16.840.1.113883.4.6"/><assignedPerson><name><family>MEDITECH</family><given>ALI</given></name></assignedPerson><representedOrganization><!-- NPI of Organization --><id nullFlavor="UNK" root="2.16.840.1.113883.4.6"/><name>CANTON MEDICAL CENTER OF MASSACHUSETTS-North Canton Facilit</name><telecom use="WP" value="tel:+1(781)821-3001"/></representedOrganization></assignedAuthor></author><!-- Drug vehicle IGpg478--><participant typeCode="CSM"><participantRole classCode="MANU"><templateId root="2.16.840.1.113883.10.20.22.4.24"/><code code="412307009" codeSystem="2.16.840.1.113883.6.96" displayName="Drug vehicle"/><playingEntity classCode="MMAT"><code nullFlavor="UNK"/><name/></playingEntity></participantRole></participant><!-- Indication - Reason for medication IGpg570 --><entryRelationship typeCode="RSON"><observation classCode="OBS" moodCode="EVN"><templateId extension="2014-06-09" root="2.16.840.1.113883.10.20.22.4.19"/><templateId root="2.16.840.1.113883.10.20.22.4.19"/><id nullFlavor="NA"/><code code="ASSERTION" codeSystem="2.16.840.1.113883.5.4"/><statusCode code="completed"/><value nullFlavor="UNK" xsi:type="CD"/></observation></entryRelationship><entryRelationship inversionInd="true" typeCode="COMP"><!-- Sequence in administration series --><sequenceNumber value="2"/><!-- Substance Administered Act IGpg847 --><act classCode="ACT" moodCode="EVN"><templateId root="2.16.840.1.113883.10.20.22.4.118"/><id root="fbf89f34-b024-4906-9512-9f80db02a2d1"/><code code="416118004" codeSystem="2.16.840.1.113883.6.96" codeSystemName="SNOMED CT" displayName="Administration"/><statusCode code="completed"/><effectiveTime value="20220324093400-0400"/></act></entryRelationship></substanceAdministration></entry></section></component><!-- Procedures Section (entries required) (V2) section: identifier urn:hl7ii:2.16.840.1.113883.10.20.22.2.7.1:2014-06-09 IGpg389--><component><section nullFlavor="NI"><templateId extension="2014-06-09" root="2.16.840.1.113883.10.20.22.2.7"/><templateId extension="2014-06-09" root="2.16.840.1.113883.10.20.22.2.7.1"/><templateId root="2.16.840.1.113883.10.20.22.2.7.1"/><code code="47519-4" codeSystem="2.16.840.1.113883.6.1" codeSystemName="LOINC" displayName="PROCEDURES"/><title>Procedures</title><text>No procedure information available</text></section></component><!-- Results Section (entries required) (V3) IGpg 398 --><component><section nullFlavor="NI"><templateId extension="2015-08-01" root="2.16.840.1.113883.10.20.22.2.3.1"/><templateId root="2.16.840.1.113883.10.20.22.2.3.1"/><code code="30954-2" codeSystem="2.16.840.1.113883.6.1" codeSystemName="2.16.840.1.113883.6.1" displayName="RELEVANT DIAGNOSTIC TESTS AND/OR LABORATORY DATA"/><title>Relevant Diagnostic Tests and/or Laboratory Data</title><text>No known relevant diagnostic tests and/or laboratory data.</text></section></component><!-- Vital Signs Section (entries required) (V3) IGpg412 --><component><section><templateId extension="2015-08-01" root="2.16.840.1.113883.10.20.22.2.4.1"/><templateId root="2.16.840.1.113883.10.20.22.2.4.1"/><code code="8716-3" codeSystem="2.16.840.1.113883.6.1" codeSystemName="LOINC" displayName="VITAL SIGNS"/><title>Vital Signs</title><text><table><thead><tr><th>Vital Reading</th><th>Result</th><th>Reference Range</th><th>Collection Date/Time</th></tr></thead><tbody><tr><td>Height</td><td ID="vitalSign-1.1">65 [in_i]</td><td/><td>March 14th, 2022 1:48pm</td></tr><tr><td>Height</td><td ID="vitalSign-1.2">165.1 cm</td><td/><td>March 14th, 2022 1:48pm</td></tr><tr><td>Weight</td><td ID="vitalSign-1.3">150.00 [lb_av]</td><td/><td>March 14th, 2022 1:48pm</td></tr><tr><td>Weight</td><td ID="vitalSign-1.4">68.039 kg</td><td/><td>March 14th, 2022 1:48pm</td></tr><tr><td>BMI (Body Mass Index)</td><td ID="vitalSign-1.5">25.0 kg/m2</td><td/><td>March 14th, 2022 1:48pm</td></tr></tbody></table></text><!-- ** Vital signs organizer (V3) ** IGpg873--><entry typeCode="DRIV"><organizer classCode="CLUSTER" moodCode="EVN"><templateId extension="2015-08-01" root="2.16.840.1.113883.10.20.22.4.26"/><templateId root="2.16.840.1.113883.10.20.22.4.26"/><id root="64bbf439-233c-4677-a9c3-321137caea77"/><code code="46680005" codeSystem="2.16.840.1.113883.6.96" codeSystemName="SNOMED CT" displayName="Vital signs"><translation code="74728-7" codeSystem="2.16.840.1.113883.6.1" codeSystemName="LOINC" displayName="Vital signs"/></code><statusCode code="completed"/><effectiveTime><low value="20220312194500-0400"/><high nullFlavor="UNK"/></effectiveTime><!-- ** Vital sign observation (V2) IGpg869 --><component><observation classCode="OBS" moodCode="EVN"><templateId extension="2014-06-09" root="2.16.840.1.113883.10.20.22.4.27"/><templateId root="2.16.840.1.113883.10.20.22.4.27"/><id root="17867d40-a3bf-11ec-81e0-9e7eef92c510"/><code code="8302-2" codeSystem="2.16.840.1.113883.6.1" codeSystemName="LOINC" displayName="Height"/><text><reference value="#vitalSign-1.1"/></text><statusCode code="completed"/><effectiveTime value="20220314134800-0400"/><value unit="[in_i]" value="65" xsi:type="PQ"/><author><!-- Provenance - Author Participation --><templateId root="2.16.840.1.113883.10.20.22.4.119"/><templateId extension="2019-10-01" root="2.16.840.1.113883.10.20.22.5.6"/><time value="20220314134800-0400"/><assignedAuthor><!-- NPI of Author --><id extension="1111111112" root="2.16.840.1.113883.4.6"/><assignedPerson><name><family>MEDITECH</family><given>ALI</given></name></assignedPerson><representedOrganization><!-- NPI of Organization --><id nullFlavor="UNK" root="2.16.840.1.113883.4.6"/><name>CANTON MEDICAL CENTER OF MASSACHUSETTS-North Canton Facilit</name><telecom use="WP" value="tel:+1(781)821-3001"/></representedOrganization></assignedAuthor></author></observation></component><!-- ** Vital sign observation (V2) IGpg869 --><component><observation classCode="OBS" moodCode="EVN"><templateId extension="2014-06-09" root="2.16.840.1.113883.10.20.22.4.27"/><templateId root="2.16.840.1.113883.10.20.22.4.27"/><id root="17867d41-a3bf-11ec-81e0-9e7eef92c510"/><code code="8302-2" codeSystem="2.16.840.1.113883.6.1" codeSystemName="LOINC" displayName="Height"/><text><reference value="#vitalSign-1.2"/></text><statusCode code="completed"/><effectiveTime value="20220314134800-0400"/><value unit="cm" value="165.1" xsi:type="PQ"/><author><!-- Provenance - Author Participation --><templateId root="2.16.840.1.113883.10.20.22.4.119"/><templateId extension="2019-10-01" root="2.16.840.1.113883.10.20.22.5.6"/><time value="20220314134800-0400"/><assignedAuthor><!-- NPI of Author --><id extension="1111111112" root="2.16.840.1.113883.4.6"/><assignedPerson><name><family>MEDITECH</family><given>ALI</given></name></assignedPerson><representedOrganization><!-- NPI of Organization --><id nullFlavor="UNK" root="2.16.840.1.113883.4.6"/><name>CANTON MEDICAL CENTER OF MASSACHUSETTS-North Canton Facilit</name><telecom use="WP" value="tel:+1(781)821-3001"/></representedOrganization></assignedAuthor></author></observation></component><!-- ** Vital sign observation (V2) IGpg869 --><component><observation classCode="OBS" moodCode="EVN"><templateId extension="2014-06-09" root="2.16.840.1.113883.10.20.22.4.27"/><templateId root="2.16.840.1.113883.10.20.22.4.27"/><id root="17867d42-a3bf-11ec-81e0-9e7eef92c510"/><code code="29463-7" codeSystem="2.16.840.1.113883.6.1" codeSystemName="LOINC" displayName="Weight"/><text><reference value="#vitalSign-1.3"/></text><statusCode code="completed"/><effectiveTime value="20220314134800-0400"/><value unit="[lb_av]" value="150.00" xsi:type="PQ"/><author><!-- Provenance - Author Participation --><templateId root="2.16.840.1.113883.10.20.22.4.119"/><templateId extension="2019-10-01" root="2.16.840.1.113883.10.20.22.5.6"/><time value="20220314134800-0400"/><assignedAuthor><!-- NPI of Author --><id extension="1111111112" root="2.16.840.1.113883.4.6"/><assignedPerson><name><family>MEDITECH</family><given>ALI</given></name></assignedPerson><representedOrganization><!-- NPI of Organization --><id nullFlavor="UNK" root="2.16.840.1.113883.4.6"/><name>CANTON MEDICAL CENTER OF MASSACHUSETTS-North Canton Facilit</name><telecom use="WP" value="tel:+1(781)821-3001"/></representedOrganization></assignedAuthor></author></observation></component><!-- ** Vital sign observation (V2) IGpg869 --><component><observation classCode="OBS" moodCode="EVN"><templateId extension="2014-06-09" root="2.16.840.1.113883.10.20.22.4.27"/><templateId root="2.16.840.1.113883.10.20.22.4.27"/><id root="17867d43-a3bf-11ec-81e0-9e7eef92c510"/><code code="29463-7" codeSystem="2.16.840.1.113883.6.1" codeSystemName="LOINC" displayName="Weight"/><text><reference value="#vitalSign-1.4"/></text><statusCode code="completed"/><effectiveTime value="20220314134800-0400"/><value unit="kg" value="68.039" xsi:type="PQ"/><author><!-- Provenance - Author Participation --><templateId root="2.16.840.1.113883.10.20.22.4.119"/><templateId extension="2019-10-01" root="2.16.840.1.113883.10.20.22.5.6"/><time value="20220314134800-0400"/><assignedAuthor><!-- NPI of Author --><id extension="1111111112" root="2.16.840.1.113883.4.6"/><assignedPerson><name><family>MEDITECH</family><given>ALI</given></name></assignedPerson><representedOrganization><!-- NPI of Organization --><id nullFlavor="UNK" root="2.16.840.1.113883.4.6"/><name>CANTON MEDICAL CENTER OF MASSACHUSETTS-North Canton Facilit</name><telecom use="WP" value="tel:+1(781)821-3001"/></representedOrganization></assignedAuthor></author></observation></component><!-- ** Vital sign observation (V2) IGpg869 --><component><observation classCode="OBS" moodCode="EVN"><templateId extension="2014-06-09" root="2.16.840.1.113883.10.20.22.4.27"/><templateId root="2.16.840.1.113883.10.20.22.4.27"/><id root="17867d44-a3bf-11ec-81e0-9e7eef92c510"/><code code="39156-5" codeSystem="2.16.840.1.113883.6.1" codeSystemName="LOINC" displayName="BMI (Body Mass Index)"/><text><reference value="#vitalSign-1.5"/></text><statusCode code="completed"/><effectiveTime value="20220314134800-0400"/><value unit="kg/m2" value="25.0" xsi:type="PQ"/><author><!-- Provenance - Author Participation --><templateId root="2.16.840.1.113883.10.20.22.4.119"/><templateId extension="2019-10-01" root="2.16.840.1.113883.10.20.22.5.6"/><time value="20220314134800-0400"/><assignedAuthor><!-- NPI of Author --><id extension="1111111112" root="2.16.840.1.113883.4.6"/><assignedPerson><name><family>MEDITECH</family><given>ALI</given></name></assignedPerson><representedOrganization><!-- NPI of Organization --><id nullFlavor="UNK" root="2.16.840.1.113883.4.6"/><name>CANTON MEDICAL CENTER OF MASSACHUSETTS-North Canton Facilit</name><telecom use="WP" value="tel:+1(781)821-3001"/></representedOrganization></assignedAuthor></author></observation></component></organizer></entry></section></component><!-- Medications Administered Section IGpg334 --><component><section><templateId extension="2014-06-09" root="2.16.840.1.113883.10.20.22.2.38"/><code code="29549-3" codeSystem="2.16.840.1.113883.6.1" codeSystemName="LOINC" displayName="MEDICATIONS ADMINISTERED"/><title>Administered Medications</title><text><table><thead><tr><th>Medication</th><th>Dose</th><th>Units</th><th>Route</th><th>Directions</th><th>Qty</th><th>Days</th><th>Start Date</th><th>End Date</th><th>Instructions</th></tr></thead><tbody><tr><td ID="rxmed-1">ZIDO100C4 (Zidovudine                                ) 100 MG TABLET</td><td>100</td><td>MG</td><td>ORAL</td><td ID="rxsig-1">Q6H</td><td/><td/><td>March 12th, 2022 7:49pm</td><td>March 12th, 2022 7:49pm</td><td/></tr><tr><td ID="rxmed-2">RIFA150C15 (Rifampin                                  ) 150 MG CAPSULE</td><td>150</td><td>MG</td><td>ORAL</td><td ID="rxsig-2">Q6H</td><td/><td/><td>March 24th, 2022 9:34am</td><td>March 24th, 2022 9:34am</td><td/></tr></tbody></table></text><entry typeCode="DRIV"><substanceAdministration classCode="SBADM" moodCode="EVN"><!-- Medication Activity (V2) IGpg589 --><templateId extension="2014-06-09" root="2.16.840.1.113883.10.20.22.4.16"/><templateId root="2.16.840.1.113883.10.20.22.4.16"/><id root="a3266d97-ce19-11ec-81e1-8465ad080d41"/><statusCode code="active"/><effectiveTime xsi:type="IVL_TS"><low value="20220312194900-0400"/><high value="20220312194900-0400"/></effectiveTime><routeCode nullFlavor="UNK"/><doseQuantity value="100"/><administrationUnitCode code="C42998" codeSystem="2.16.840.1.113883.3.26.1.1" codeSystemName="National Cancer Institute (NCI) Thesaurus" displayName="TABLET"/><consumable><!-- Medication Information (V2) IGpg604 --><manufacturedProduct classCode="MANU"><templateId extension="2014-06-09" root="2.16.840.1.113883.10.20.22.4.23"/><templateId root="2.16.840.1.113883.10.20.22.4.23"/><id root="64dc158d-a1c7-4de6-9529-393919edb4d5"/><manufacturedMaterial><code code="198352" codeSystem="2.16.840.1.113883.6.88" codeSystemName="RxNorm" displayName="ZIDO100C4"><originalText><reference value="#rxmed-1"/></originalText></code></manufacturedMaterial><manufacturerOrganization><name nullFlavor="UNK"/></manufacturerOrganization></manufacturedProduct></consumable><author><!-- Provenance - Author Participation --><templateId root="2.16.840.1.113883.10.20.22.4.119"/><templateId extension="2019-10-01" root="2.16.840.1.113883.10.20.22.5.6"/><time value="20220312184900-0500"/><assignedAuthor><!-- NPI of Author --><id extension="1111111112" root="2.16.840.1.113883.4.6"/><assignedPerson><name><family>MEDITECH</family><given>ALI</given></name></assignedPerson><representedOrganization><!-- NPI of Organization --><id nullFlavor="UNK" root="2.16.840.1.113883.4.6"/><name>CANTON MEDICAL CENTER OF MASSACHUSETTS-North Canton Facilit</name><telecom use="WP" value="tel:+1(781)821-3001"/></representedOrganization></assignedAuthor></author><!-- Drug vehicle IGpg478--><participant typeCode="CSM"><participantRole classCode="MANU"><templateId root="2.16.840.1.113883.10.20.22.4.24"/><code code="412307009" codeSystem="2.16.840.1.113883.6.96" displayName="Drug vehicle"/><playingEntity classCode="MMAT"><code nullFlavor="UNK"/><name/></playingEntity></participantRole></participant><!-- Indication - Reason for medication IGpg570 --><entryRelationship typeCode="RSON"><observation classCode="OBS" moodCode="EVN"><templateId extension="2014-06-09" root="2.16.840.1.113883.10.20.22.4.19"/><templateId root="2.16.840.1.113883.10.20.22.4.19"/><id nullFlavor="NA"/><code code="ASSERTION" codeSystem="2.16.840.1.113883.5.4"/><statusCode code="completed"/><value nullFlavor="UNK" xsi:type="CD"/></observation></entryRelationship><!-- Administration (Dispense) Details IGpg598--><entryRelationship typeCode="REFR"><supply classCode="SPLY" moodCode="EVN"><templateId extension="2014-06-09" root="2.16.840.1.113883.10.20.22.4.18"/><templateId root="2.16.840.1.113883.10.20.22.4.18"/><id extension="040703" root="1.3.6.1.4.1.24310"/><statusCode code="completed"/><effectiveTime value="20220312"/><product><!-- Medication Information (V2) IGpg604 --><manufacturedProduct classCode="MANU"><templateId extension="2014-06-09" root="2.16.840.1.113883.10.20.22.4.23"/><templateId root="2.16.840.1.113883.10.20.22.4.23"/><id root="33b16f8d-8d8b-4e42-987e-549f1573a2fc"/><manufacturedMaterial><code code="198352" codeSystem="2.16.840.1.113883.6.88" codeSystemName="RxNorm" displayName="ZIDO100C4"/></manufacturedMaterial><manufacturerOrganization><name nullFlavor="UNK"/></manufacturerOrganization></manufacturedProduct></product><performer><assignedEntity><id nullFlavor="UNK"/><code nullFlavor="UNK"/><addr><streetAddressLine nullFlavor="UNK"/><city nullFlavor="UNK"/><state nullFlavor="UNK"/><postalCode nullFlavor="UNK"/></addr><assignedPerson><name><family>MCUTLER</family></name></assignedPerson><representedOrganization><id nullFlavor="UNK"/><addr><streetAddressLine nullFlavor="UNK"/><city nullFlavor="UNK"/><state nullFlavor="UNK"/><postalCode nullFlavor="UNK"/></addr></representedOrganization></assignedEntity></performer></supply></entryRelationship><!-- Medication Supply Order (V2) IGPG608 --><entryRelationship typeCode="REFR"><supply classCode="SPLY" moodCode="INT"><templateId extension="2014-06-09" root="2.16.840.1.113883.10.20.22.4.17"/><templateId root="2.16.840.1.113883.10.20.22.4.17"/><id root="0da994e0-a38b-48be-9184-0e2b426b5697"/><statusCode code="completed"/><effectiveTime xsi:type="IVL_TS"><high nullFlavor="UNK"/></effectiveTime><product><!-- Medication Information (V2) IGpg604 --><manufacturedProduct classCode="MANU"><templateId extension="2014-06-09" root="2.16.840.1.113883.10.20.22.4.23"/><templateId root="2.16.840.1.113883.10.20.22.4.23"/><id root="2d459768-20d7-40e1-a026-ce0f706ee90f"/><manufacturedMaterial><code code="198352" codeSystem="2.16.840.1.113883.6.88" codeSystemName="RxNorm" displayName="ZIDO100C4"/></manufacturedMaterial><manufacturerOrganization><name nullFlavor="UNK"/></manufacturerOrganization></manufacturedProduct></product></supply></entryRelationship><entryRelationship typeCode="COMP"><!-- Medication Free Text Sig IGpg602 --><substanceAdministration classCode="SBADM" moodCode="EVN"><templateId root="2.16.840.1.113883.10.20.22.4.147"/><code code="76662-6" codeSystem="2.16.840.1.113883.6.1" codeSystemName="LOINC" displayName="Medication Instructions"/><text><reference value="#rxsig-1"/></text><consumable><manufacturedProduct><manufacturedLabeledDrug nullFlavor="NA"/></manufacturedProduct></consumable></substanceAdministration></entryRelationship></substanceAdministration></entry><entry typeCode="DRIV"><substanceAdministration classCode="SBADM" moodCode="EVN"><!-- Medication Activity (V2) IGpg589 --><templateId extension="2014-06-09" root="2.16.840.1.113883.10.20.22.4.16"/><templateId root="2.16.840.1.113883.10.20.22.4.16"/><id root="a3266d98-ce19-11ec-81e1-8465ad080d41"/><statusCode code="active"/><effectiveTime xsi:type="IVL_TS"><low value="20220324093400-0400"/><high value="20220324093400-0400"/></effectiveTime><routeCode nullFlavor="UNK"/><doseQuantity value="150"/><consumable><!-- Medication Information (V2) IGpg604 --><manufacturedProduct classCode="MANU"><templateId extension="2014-06-09" root="2.16.840.1.113883.10.20.22.4.23"/><templateId root="2.16.840.1.113883.10.20.22.4.23"/><id root="6c744c3b-02fe-48c9-b288-2f27eeb27246"/><manufacturedMaterial><code code="198201" codeSystem="2.16.840.1.113883.6.88" codeSystemName="RxNorm" displayName="RIFA150C15"><originalText><reference value="#rxmed-2"/></originalText></code></manufacturedMaterial><manufacturerOrganization><name nullFlavor="UNK"/></manufacturerOrganization></manufacturedProduct></consumable><author><!-- Provenance - Author Participation --><templateId root="2.16.840.1.113883.10.20.22.4.119"/><templateId extension="2019-10-01" root="2.16.840.1.113883.10.20.22.5.6"/><time value="20220324093400-0400"/><assignedAuthor><!-- NPI of Author --><id extension="1111111112" root="2.16.840.1.113883.4.6"/><assignedPerson><name><family>MEDITECH</family><given>ALI</given></name></assignedPerson><representedOrganization><!-- NPI of Organization --><id nullFlavor="UNK" root="2.16.840.1.113883.4.6"/><name>CANTON MEDICAL CENTER OF MASSACHUSETTS-North Canton Facilit</name><telecom use="WP" value="tel:+1(781)821-3001"/></representedOrganization></assignedAuthor></author><!-- Drug vehicle IGpg478--><participant typeCode="CSM"><participantRole classCode="MANU"><templateId root="2.16.840.1.113883.10.20.22.4.24"/><code code="412307009" codeSystem="2.16.840.1.113883.6.96" displayName="Drug vehicle"/><playingEntity classCode="MMAT"><code nullFlavor="UNK"/><name/></playingEntity></participantRole></participant><!-- Indication - Reason for medication IGpg570 --><entryRelationship typeCode="RSON"><observation classCode="OBS" moodCode="EVN"><templateId extension="2014-06-09" root="2.16.840.1.113883.10.20.22.4.19"/><templateId root="2.16.840.1.113883.10.20.22.4.19"/><id nullFlavor="NA"/><code code="ASSERTION" codeSystem="2.16.840.1.113883.5.4"/><statusCode code="completed"/><value nullFlavor="UNK" xsi:type="CD"/></observation></entryRelationship><!-- Administration (Dispense) Details IGpg598--><entryRelationship typeCode="REFR"><supply classCode="SPLY" moodCode="EVN"><templateId extension="2014-06-09" root="2.16.840.1.113883.10.20.22.4.18"/><templateId root="2.16.840.1.113883.10.20.22.4.18"/><id extension="040802" root="1.3.6.1.4.1.24310"/><statusCode code="completed"/><effectiveTime value="20220324"/><product><!-- Medication Information (V2) IGpg604 --><manufacturedProduct classCode="MANU"><templateId extension="2014-06-09" root="2.16.840.1.113883.10.20.22.4.23"/><templateId root="2.16.840.1.113883.10.20.22.4.23"/><id root="cb0990e1-e77a-4cd8-967a-724e1876f0b2"/><manufacturedMaterial><code code="198201" codeSystem="2.16.840.1.113883.6.88" codeSystemName="RxNorm" displayName="RIFA150C15"/></manufacturedMaterial><manufacturerOrganization><name nullFlavor="UNK"/></manufacturerOrganization></manufacturedProduct></product><performer><assignedEntity><id nullFlavor="UNK"/><code nullFlavor="UNK"/><addr><streetAddressLine nullFlavor="UNK"/><city nullFlavor="UNK"/><state nullFlavor="UNK"/><postalCode nullFlavor="UNK"/></addr><assignedPerson><name><family>MCUTLER</family></name></assignedPerson><representedOrganization><id nullFlavor="UNK"/><addr><streetAddressLine nullFlavor="UNK"/><city nullFlavor="UNK"/><state nullFlavor="UNK"/><postalCode nullFlavor="UNK"/></addr></representedOrganization></assignedEntity></performer></supply></entryRelationship><!-- Medication Supply Order (V2) IGPG608 --><entryRelationship typeCode="REFR"><supply classCode="SPLY" moodCode="INT"><templateId extension="2014-06-09" root="2.16.840.1.113883.10.20.22.4.17"/><templateId root="2.16.840.1.113883.10.20.22.4.17"/><id root="953cf063-2bfb-40da-b5df-e25db48c2989"/><statusCode code="completed"/><effectiveTime xsi:type="IVL_TS"><high nullFlavor="UNK"/></effectiveTime><product><!-- Medication Information (V2) IGpg604 --><manufacturedProduct classCode="MANU"><templateId extension="2014-06-09" root="2.16.840.1.113883.10.20.22.4.23"/><templateId root="2.16.840.1.113883.10.20.22.4.23"/><id root="cd1dd840-d2dc-46f0-8212-1b5d9748c7ed"/><manufacturedMaterial><code code="198201" codeSystem="2.16.840.1.113883.6.88" codeSystemName="RxNorm" displayName="RIFA150C15"/></manufacturedMaterial><manufacturerOrganization><name nullFlavor="UNK"/></manufacturerOrganization></manufacturedProduct></product></supply></entryRelationship><entryRelationship typeCode="COMP"><!-- Medication Free Text Sig IGpg602 --><substanceAdministration classCode="SBADM" moodCode="EVN"><templateId root="2.16.840.1.113883.10.20.22.4.147"/><code code="76662-6" codeSystem="2.16.840.1.113883.6.1" codeSystemName="LOINC" displayName="Medication Instructions"/><text><reference value="#rxsig-2"/></text><consumable><manufacturedProduct><manufacturedLabeledDrug nullFlavor="NA"/></manufacturedProduct></consumable></substanceAdministration></entryRelationship></substanceAdministration></entry></section></component><!-- Encounters Section IGpg287--><component><section><templateId root="2.16.840.1.113883.10.20.22.2.22"/><templateId extension="2015-08-01" root="2.16.840.1.113883.10.20.22.2.22"/><templateId root="2.16.840.1.113883.10.20.22.2.22.1"/><templateId extension="2015-08-01" root="2.16.840.1.113883.10.20.22.2.22.1"/><code code="46240-8" codeSystem="2.16.840.1.113883.6.1" codeSystemName="LOINC" displayName="History of encounters"/><title>Encounters</title><text><table><thead><tr><th>Encounter</th><th>Location(s)</th><th>Arrival/Admit Date</th><th>Discharge/Depart Date</th><th>Provider(s)</th></tr></thead><tbody><tr><td ID="encounter-1">Admitted Inpatient</td><td>Dot Facility (No ARM)</td><td>March 12th, 2022 7:45pm</td><td/><td>MCUTLER</td></tr></tbody></table><br/><table><thead><tr><th>Recent Diagnosis</th><th>Onset Date</th></tr></thead><tbody><tr><td ID="diagnosis-1.0">Anthrax</td><td/></tr></tbody></table></text><!-- Encounter Activity IGpg479--><entry typeCode="DRIV"><encounter classCode="ENC" moodCode="EVN"><templateId extension="2015-08-01" root="2.16.840.1.113883.10.20.22.4.49"/><templateId root="2.16.840.1.113883.10.20.22.4.49"/><id root="8589d447-a267-11ec-81e0-9e7eef92c510"/><id extension="0000016868" root="1.3.6.1.4.1.24310"/><code nullFlavor="UNK"><originalText><reference value="#encounter-1"/></originalText></code><effectiveTime><low value="20220312194500-0400"/></effectiveTime><!-- Provider Detail --><performer><assignedEntity><!-- Provider NPI --><id nullFlavor="NI" root="2.16.840.1.113883.4.6"/><code nullFlavor="UNK"/></assignedEntity></performer><author><!-- Provenance - Author Participation --><templateId root="2.16.840.1.113883.10.20.22.4.119"/><templateId extension="2019-10-01" root="2.16.840.1.113883.10.20.22.5.6"/><time value="20220324110700-0400"/><assignedAuthor><!-- NPI of Author --><id extension="1111111112" root="2.16.840.1.113883.4.6"/><assignedPerson><name><family>MEDITECH</family><given>ALI</given></name></assignedPerson><representedOrganization><!-- NPI of Organization --><id extension="9390001110" root="2.16.840.1.113883.4.6"/><name>Meditech Facility Author</name><telecom use="WP" value="tel:+1(508)945-6522"/></representedOrganization></assignedAuthor></author><!-- Service Location --><participant typeCode="LOC"><participantRole classCode="SDLOC"><templateId root="2.16.840.1.113883.10.20.22.4.32"/><code code="GIM" codeSystem="2.16.840.1.113883.5.111" codeSystemName="RoleCode" displayName="General internal medicine clinic"/><addr><streetAddressLine nullFlavor="UNK"/><city nullFlavor="UNK"/><state nullFlavor="UNK"/><postalCode nullFlavor="UNK"/></addr><playingEntity classCode="PLC"><name>Dot Facility (No ARM)</name></playingEntity></participantRole></participant><!-- Encounter Diagnosis Section IGpg484 --><entryRelationship typeCode="SUBJ"><act classCode="ACT" moodCode="EVN"><templateId extension="2015-08-01" root="2.16.840.1.113883.10.20.22.4.80"/><templateId root="2.16.840.1.113883.10.20.22.4.80"/><code code="29308-4" codeSystem="2.16.840.1.113883.6.1" codeSystemName="LOINC" displayName="Diagnosis"/><!-- Problem Observation IGpg737 --><entryRelationship typeCode="SUBJ"><observation classCode="OBS" moodCode="EVN" negationInd="false"><templateId root="2.16.840.1.113883.10.20.22.4.4"/><templateId extension="2015-08-01" root="2.16.840.1.113883.10.20.22.4.4"/><!-- [eICR R2 STU1.1] Initial Case Report Trigger Code Problem Observation IGpg187--><templateId extension="2016-12-01" root="2.16.840.1.113883.10.20.15.2.3.3"/><id root="3a708248-e634-473b-8e64-e569e62d418d"/><code code="64572001" codeSystem="2.16.840.1.113883.6.96" codeSystemName="SNOMED CT" displayName="Condition"><translation code="75323-6" codeSystem="2.16.840.1.113883.6.1" codeSystemName="LOINC" displayName="Condition"/></code><statusCode code="completed"/><!-- Diagnosis Effective Time --><effectiveTime><low nullFlavor="UNK"/></effectiveTime><!-- Diagnosis Codes --><value code="A22.9" codeSystem="2.16.840.1.113883.6.90" codeSystemName="ICD10" displayName="Anthrax" sdtc:valueSet="2.16.840.1.114222.4.11.7508" sdtc:valueSetVersion="2022-01-12" xsi:type="CD"><originalText><reference value="#diagnosis-1.0"/></originalText><translation code="409498004" codeSystem="2.16.840.1.113883.6.96" codeSystemName="SNOMED CT" displayName="Anthrax"/><translation code="022.9" codeSystem="2.16.840.1.113883.6.103" codeSystemName="ICD9" displayName="Anthrax"/></value></observation></entryRelationship></act></entryRelationship></encounter></entry></section></component><component><section><templateId root="2.16.840.1.113883.10.20.22.2.8"/><code code="51848-0" codeSystem="2.16.840.1.113883.6.1" codeSystemName="LOINC" displayName="ASSESSMENTS"/><title>Assessments</title><text><table><thead><tr><th>Diagnosis</th><th>Onset Date</th><th>Resolution</th><th>Status</th></tr></thead><tbody><tr><td>Anthrax</td><td/><td/><td>Active</td></tr></tbody></table></text></section></component><!-- Plan of Treatment Section (V2) IGpg357 --><component><section><templateId extension="2014-06-09" root="2.16.840.1.113883.10.20.22.2.10"/><templateId root="2.16.840.1.113883.10.20.22.2.10"/><code code="18776-5" codeSystem="2.16.840.1.113883.6.1" codeSystemName="LOINC" displayName="Treatment plan"/><title>Plan of Treatment</title><text><content styleCode="Bold">Future Tests</content><br/>
Future scheduled test information is unavailable

<br/><content styleCode="Bold">Pending Tests</content><br/>
Pending diagnostic test information is unavailable

<br/><content styleCode="Bold">Future Visits</content><br/>
Future appointment information is unavailable

<br/><content styleCode="Bold">Referrals to Other Providers</content><br/>
Referral information is unavailable

<br/><content styleCode="Bold">Future Procedures</content><br/>
Future procedure information is unavailable

<br/><content styleCode="Bold">Future Medications</content><br/><table><thead><tr><th>Medication Name</th><th>Start Date</th><th>Instructions</th></tr></thead><tbody><tr><td>Dapsone (Topical) - RXCUI C1741905 (DAPSONE7.5 %) 7.5 % GEL OINTMENT</td><td>March 24th, 2022 9:38am</td><td/></tr></tbody></table><br/><content styleCode="Bold">Patient Instructions</content><br/>
Patient instructions are unavailable

</text><!-- Planned Medication Activity (V2) IGpg680 --><entry><substanceAdministration classCode="SBADM" moodCode="INT"><templateId extension="2014-06-09" root="2.16.840.1.113883.10.20.22.4.42"/><templateId root="2.16.840.1.113883.10.20.22.4.42"/><id root="66d08d46-ab7b-11ec-81e0-9e7eef92c510"/><statusCode code="active"/><!-- The effectiveTime in a planned medication activity represents the time that the medication activity should occur. --><effectiveTime value="20220324093800-0400"/><routeCode nullFlavor="UNK"/><doseQuantity value="1"/><consumable><manufacturedProduct classCode="MANU"><!-- Medication Information (V2) IGpg604 --><templateId extension="2014-06-09" root="2.16.840.1.113883.10.20.22.4.23"/><templateId root="2.16.840.1.113883.10.20.22.4.23"/><id root="8697748a-d7e0-4244-aa7a-9efbb89a903b"/><manufacturedMaterial><code code="1741905" codeSystem="2.16.840.1.113883.6.88" codeSystemName="RxNorm" displayName="Dapsone (Topical) - RXCUI C1741905"/></manufacturedMaterial><manufacturerOrganization><name nullFlavor="UNK"/></manufacturerOrganization></manufacturedProduct></consumable><author><!-- Provenance - Author Participation --><templateId root="2.16.840.1.113883.10.20.22.4.119"/><templateId extension="2019-10-01" root="2.16.840.1.113883.10.20.22.5.6"/><time value="20220324093800-0400"/><assignedAuthor><!-- NPI of Author --><id extension="1111111112" root="2.16.840.1.113883.4.6"/><assignedPerson><name><family>MEDITECH</family><given>ALI</given></name></assignedPerson><representedOrganization><!-- NPI of Organization --><id nullFlavor="UNK" root="2.16.840.1.113883.4.6"/><name>CANTON MEDICAL CENTER OF MASSACHUSETTS-North Canton Facilit</name><telecom use="WP" value="tel:+1(781)821-3001"/></representedOrganization></assignedAuthor></author><!-- Drug vehicle IGpg478 --><participant typeCode="CSM"><participantRole classCode="MANU"><templateId root="2.16.840.1.113883.10.20.22.4.24"/><code code="412307009" codeSystem="2.16.840.1.113883.6.96" displayName="Drug vehicle"/><playingEntity classCode="MMAT"><code nullFlavor="UNK"/><name/></playingEntity></participantRole></participant><!-- Indication - Reason for medication IGpg570 --><entryRelationship typeCode="RSON"><observation classCode="OBS" moodCode="EVN"><templateId extension="2014-06-09" root="2.16.840.1.113883.10.20.22.4.19"/><templateId root="2.16.840.1.113883.10.20.22.4.19"/><id nullFlavor="NA"/><code code="ASSERTION" codeSystem="2.16.840.1.113883.5.4"/><statusCode code="completed"/><value nullFlavor="UNK" xsi:type="CD"/></observation></entryRelationship><!-- Medication Supply Order (V2) IGPG608 --><entryRelationship><supply classCode="SPLY" moodCode="INT"><templateId extension="2014-06-09" root="2.16.840.1.113883.10.20.22.4.17"/><templateId root="2.16.840.1.113883.10.20.22.4.17"/><id root="f5cfbfd2-e508-4584-931a-a3ed9f01a3a2"/><statusCode code="completed"/><effectiveTime xsi:type="IVL_TS"><high nullFlavor="UNK"/></effectiveTime><repeatNumber value="0"/><quantity value="3"/><product><!-- Medication Information (V2) IGpg604 --><manufacturedProduct><code code="1741905" codeSystem="2.16.840.1.113883.6.88" codeSystemName="RxNorm" displayName="Dapsone (Topical) - RXCUI C1741905"/></manufacturedProduct><manufacturerOrganization><name nullFlavor="UNK"/></manufacturerOrganization></product></supply></entryRelationship></substanceAdministration></entry></section></component></structuredBody></component></ClinicalDocument>